shrpi/__init__.py
shrpi/__main__.py
shrpi/cli.py
shrpi/const.py
shrpi/daemon.py
shrpi/example.py
shrpi/i2c.py
shrpi/server.py
shrpi/state_machine.py
shrpid-2.2.6.dist-info/METADATA
shrpid-2.2.6.dist-info/WHEEL
shrpid-2.2.6.dist-info/entry_points.txt
shrpid-2.2.6.dist-info/licenses/LICENSE
shrpid-2.2.6.dist-info/RECORD
