Metadata-Version: 2.4
Name: shrpid
Version: 2.2.6
Summary: shrpid is a power monitor and watchdog daemon for the SH-RPi.
Author-email: Matti Airas <matti.airas@hatlabs.fi>
License-File: LICENSE
Requires-Python: >=3.8
Requires-Dist: aiohttp>=3.10.11
Requires-Dist: dateparser>=1.2.0
Requires-Dist: loguru>=0.7.3
Requires-Dist: pyyaml>=6.0.2
Requires-Dist: rich>=13.9.4
Requires-Dist: smbus2>=0.5.0
Requires-Dist: typer>=0.15.1
